chem_dummy/__init__.py
chem_dummy/elements.py
chem_dummy/properties_of_elements.json
chem_dummy-0.1.0.dist-info/METADATA
chem_dummy-0.1.0.dist-info/WHEEL
chem_dummy-0.1.0.dist-info/RECORD
